[{"third_place": "Germany", "venue": "South Africa 2010", "champion": "Spain", "runner_up": "Netherlands"}, {"third_place": "Germany", "venue": "Germany 2006", "champion": "Italy", "runner_up": "France"}, {"third_place": "Turkey", "venue": "Korea Japan 2002", "champion": "Brazil", "runner_up": "Germany"}, {"third_place": "Croatia", "venue": "France 1998", "champion": "France", "runner_up": "Brazil"}, {"third_place": "Sweden", "venue": "USA 1994", "champion": "Brazil", "runner_up": "Italy"}, {"third_place": "Italy", "venue": "Italy 1990", "champion": "Germany FR", "runner_up": "Argentina"}, {"third_place": "France", "venue": "Mexico 1986", "champion": "Argentina", "runner_up": "Germany FR"}, {"third_place": "Poland", "venue": "Spain 1982", "champion": "Italy", "runner_up": "Germany FR"}, {"third_place": "Brazil", "venue": "Argentina 1978", "champion": "Argentina", "runner_up": "Netherlands"}, {"third_place": "Poland", "venue": "Germany 1974", "champion": "Germany FR", "runner_up": "Netherlands"}, {"third_place": "Germany FR", "venue": "Mexico 1970", "champion": "Brazil", "runner_up": "Italy"}, {"third_place": "Portugal", "venue": "England 1966", "champion": "England", "runner_up": "Germany FR"}, {"third_place": "Chile", "venue": "Chile 1962", "champion": "Brazil", "runner_up": "Czechoslovakia"}, {"third_place": "France", "venue": "Sweden 1958", "champion": "Brazil", "runner_up": "Sweden"}, {"third_place": "Austria", "venue": "Switzerland 1954", "champion": "Germany FR", "runner_up": "Hungary"}, {"third_place": "Sweden", "venue": "Brazil 1950", "champion": "Uruguay", "runner_up": "Brazil"}, {"third_place": "Brazil", "venue": "France 1938", "champion": "Italy", "runner_up": "Hungary"}, {"third_place": "Germany", "venue": "Italy 1934", "champion": "Italy", "runner_up": "Czechoslovakia"}, {"third_place": "USA", "venue": "Uruguay 1930", "champion": "Uruguay", "runner_up": "Argentina"}]